aiopypexels/__init__.py
aiopypexels/core.py
aiopypexels/exceptions/BaseException.py
aiopypexels/exceptions/ExceptionsEnum.py
aiopypexels/exceptions/PexelsNotFound.py
aiopypexels/exceptions/PexelsUnauthorised.py
aiopypexels/exceptions/__init__.py
aiopypexels/types/__init__.py
aiopypexels/types/arg_types.py
aiopypexels/types/content_types.py
aiopypexels/types/response_types.py
aiopypexels/utils/__init__.py
aiopypexels/utils/locale_enum.py
aiopypexels-1.0.1.dist-info/METADATA
aiopypexels-1.0.1.dist-info/WHEEL
aiopypexels-1.0.1.dist-info/top_level.txt
aiopypexels-1.0.1.dist-info/RECORD
