Metadata-Version: 2.1
Name: aiopypexels
Version: 1.0.1
Summary: An asynchronous wrapper for Pexels API based on aiohttp, which additionally allows to download photos in any of avaliable resolutions.
Home-page: UNKNOWN
Author: ggindinson
License: UNKNOWN
Keywords: pexels,api,photos
Platform: UNKNOWN
Classifier: Programming Language :: Python :: 3
Classifier: License :: OSI Approved :: MIT License
Classifier: Operating System :: OS Independent
Requires-Python: >=3.6
Requires-Dist: aiohttp
Requires-Dist: dacite
Requires-Dist: aiocfscrape
